diskspaced/__init__.py
diskspaced/command_line.py
diskspaced/constants.py
diskspaced/defer.py
diskspaced/grand_perspective_writer.py
diskspaced/json_writer.py
diskspaced/temporary_recursion_limit.py
diskspaced/writer.py
diskspaced-0.0.14.dist-info/LICENSE
diskspaced-0.0.14.dist-info/METADATA
diskspaced-0.0.14.dist-info/WHEEL
diskspaced-0.0.14.dist-info/entry_points.txt
diskspaced-0.0.14.dist-info/RECORD
