Metadata-Version: 2.1
Name: diskspaced
Version: 0.0.14
Summary: A utility for analyzing disk space via the CLI.
Home-page: https://github.com/dalemyers/diskspaced
License: MIT
Keywords: diskspaced,disk,space,analyzer
Author: Dale Myers
Author-email: dale@myers.io
Requires-Python: >=3.10,<4.0
Classifier: Development Status :: 3 - Alpha
Classifier: Intended Audience :: Developers
Classifier: License :: OSI Approved :: MIT License
Classifier: Programming Language :: Python :: 3
Classifier: Programming Language :: Python :: 3.10
Classifier: Programming Language :: Python :: 3.11
Classifier: Programming Language :: Python :: 3.12
Classifier: Programming Language :: Python :: 3.13
Classifier: Topic :: Software Development :: Libraries
Project-URL: Repository, https://github.com/dalemyers/diskspaced
